bryafunctions/___init__.py
bryafunctions-0.1.dist-info/LICENSE
bryafunctions-0.1.dist-info/METADATA
bryafunctions-0.1.dist-info/WHEEL
bryafunctions-0.1.dist-info/top_level.txt
bryafunctions-0.1.dist-info/RECORD
