Metadata-Version: 2.1
Name: bryafunctions
Version: 0.1
Summary: Python Functions in relation to BryaSoftware Tutorials, learn more at my GitHub or www.bryasoftware.com
Home-page: https://github.com/BryaSoftware/BryaFunctions
Author: Zac Bryant
Author-email: zac.bryant15@gmail.com
License: UNKNOWN
Platform: UNKNOWN
